ids_toolkit-1.2.5.dist-info/METADATA
ids_toolkit-1.2.5.dist-info/WHEEL
ids_toolkit/schemas/bef.json
ids_toolkit/schemas/lpr3_kontakter.json
ids_toolkit/schemas/uddf.json
ids_toolkit/schemas/lpr3_diagnoser.json
ids_toolkit/schemas/ind.json
ids_toolkit/schemas/lpr_adm.json
ids_toolkit/schemas/idan.json
ids_toolkit/schemas/lpr_bes.json
ids_toolkit/schemas/akm.json
ids_toolkit/schemas/lpr_diag.json
ids_toolkit/__init__.py
ids_toolkit/mappings/hustype.json
ids_toolkit/mappings/icd10.json
ids_toolkit/mappings/civst.json
ids_toolkit/mappings/fm_mark.json
ids_toolkit/mappings/beskst13.json
ids_toolkit/mappings/scd.json
ids_toolkit/mappings/socio13.json
ids_toolkit/mappings/family_type.json
ids_toolkit/mappings/plads.json
ids_toolkit/mappings/hfaudd.json
ids_toolkit/mappings/statsb.json
ids_toolkit/mappings/tilknyt.json
ids_toolkit/mappings/jobkat.json
ids_toolkit/mappings/pre_socio.json
ids_toolkit/mappings/reg.json
ids_toolkit-1.2.5.data/scripts/ids
ids_toolkit.libs/libbrotlicommon-a91ead09.so.1
ids_toolkit.libs/libbrotlidec-64d8a501.so.1
ids_toolkit.libs/libbz2-218c4abd.so.1.0
ids_toolkit.libs/libfontconfig-a94b4059.so.1
ids_toolkit.libs/libfreetype-fd0e5281.so.6
ids_toolkit.libs/libpng16-29896eea.so.16
ids_toolkit-1.2.5.dist-info/RECORD
